simplegrad/__init__.py
simplegrad/py.typed
simplegrad/simplegrad.cpython-312-x86_64-linux-gnu.so
simplegrad/simplegrad.pyi
simplegrad-0.0.2.dist-info/METADATA
simplegrad-0.0.2.dist-info/WHEEL
simplegrad-0.0.2.dist-info/top_level.txt
simplegrad-0.0.2.dist-info/RECORD
