Metadata-Version: 2.1
Name: simplegrad
Version: 0.0.2
Summary: Automatic differentiation library for basic arithmetic operations
Home-page: https://github.com/deniztemur00/simplegrad.git
Author: Deniz
Author-email: deniztemur00@gmail.com
License: MIT
Classifier: Programming Language :: Python :: 3
Classifier: License :: OSI Approved :: MIT License
Classifier: Operating System :: POSIX :: Linux
Requires-Python: >=3.6
